pos_fiap_couras/__init__.py
pos_fiap_couras/core.py
pos_fiap_couras_package-1.0.0.dist-info/METADATA
pos_fiap_couras_package-1.0.0.dist-info/WHEEL
pos_fiap_couras_package-1.0.0.dist-info/top_level.txt
pos_fiap_couras_package-1.0.0.dist-info/RECORD
