Metadata-Version: 2.1
Name: pos_fiap_couras-package
Version: 1.0.0
Summary: Descricao da sua lib pos_fiap_couras
Home-page: https://github.com/tadrianonet/pos_fiap_couras
Author: seu nome
Author-email: seu.email@example.com
License: MIT
